genser/__init__.py
genser/main.py
genser-1.0.1.dist-info/LICENSE
genser-1.0.1.dist-info/METADATA
genser-1.0.1.dist-info/WHEEL
genser-1.0.1.dist-info/top_level.txt
genser-1.0.1.dist-info/RECORD
