Metadata-Version: 2.1
Name: genser
Version: 1.0.1
Summary: A set of functions to transform datasets
Author: Sergei Zuev
Author-email: shoukhov@mail.ru
Classifier: Programming Language :: Python :: 3.7
Classifier: Operating System :: OS Independent
Requires-Python: >=3.6
License-File: LICENSE
